COPYING
LICENSE
MANIFEST.in
README.rst
requirements.txt
setup.py
django_livinglots_generictags.egg-info/PKG-INFO
django_livinglots_generictags.egg-info/SOURCES.txt
django_livinglots_generictags.egg-info/dependency_links.txt
django_livinglots_generictags.egg-info/requires.txt
django_livinglots_generictags.egg-info/top_level.txt
livinglots_generictags/__init__.py
livinglots_generictags/tags.py