Metadata-Version: 1.1
Name: django-livinglots-generictags
Version: 1.0
Summary: A set of helpers for creating Django template tags for models with generic relations.
Home-page: https://github.com/596acres/django-livinglots-generictags/
Author: Eric Brelsford
Author-email: eric@596acres.org
License: GNU Lesser General Public License v3 (LGPLv3)
Platform: OS Independent
Classifier: Development Status :: 5 - Production/Stable
Classifier: Environment :: Web Environment
Classifier: Framework :: Django
Classifier: Intended Audience :: Developers
Classifier: License :: OSI Approved :: GNU Affero General Public License v3 or later (AGPLv3+)
Classifier: Operating System :: OS Independent
Classifier: Programming Language :: Python
Classifier: Topic :: Internet :: WWW/HTTP :: Dynamic Content
Classifier: Topic :: Software Development
